migemo/__init__.py
migemo/__main__.py
migemo/bitvector.py
migemo/characterconverter.py
migemo/loudstrie.py
migemo/migemo-compact-dict
migemo/migemo.py
migemo/migemocompactdictionary.py
migemo/regexgenerator.py
migemo/regexoperator.py
migemo/romajiconverter.py
pymigemo-0.0.1.dist-info/LICENSE
pymigemo-0.0.1.dist-info/METADATA
pymigemo-0.0.1.dist-info/WHEEL
pymigemo-0.0.1.dist-info/entry_points.txt
pymigemo-0.0.1.dist-info/top_level.txt
pymigemo-0.0.1.dist-info/RECORD
