Metadata-Version: 2.1
Name: pymigemo
Version: 0.0.1
Summary: Migemo implementation on Python
Home-page: https://github.com/oguna/pymigemo
Author: oguna
Author-email: 
License: BSD
Platform: UNKNOWN
